__init__.py
calibration_manager.py
example_ros.py
calibration_manager-0.0.2.dist-info/LICENSE
calibration_manager-0.0.2.dist-info/METADATA
calibration_manager-0.0.2.dist-info/WHEEL
calibration_manager-0.0.2.dist-info/top_level.txt
calibration_manager-0.0.2.dist-info/RECORD
