Metadata-Version: 2.1
Name: calibration-manager
Version: 0.0.2
Summary: A general purpose, ROS installable OR pure python package for keeping track of machine calibration data.
Author-email: James Haley <J-C-Haley@users.noreply.github.com>
Project-URL: Homepage, https://github.com/J-C-Haley/calibration_manager
Project-URL: Bug Tracker, https://github.com/J-C-Haley/calibration_manager/issues
Classifier: Programming Language :: Python :: 3
Classifier: License :: OSI Approved :: BSD License
Classifier: Operating System :: OS Independent
Requires-Python: >=3.8
License-File: LICENSE
Requires-Dist: numpy
Requires-Dist: pandas
Requires-Dist: ruamel.yaml >0.17.0
